consumer_helper/__init__.py
consumer_helper/consumer_helper.py
consumer_helper-0.1.0.dist-info/METADATA
consumer_helper-0.1.0.dist-info/WHEEL
consumer_helper-0.1.0.dist-info/top_level.txt
consumer_helper-0.1.0.dist-info/RECORD
